{
  "name": "AMT Hardballer Longslide",
  "type": "weapon",
  "img": "systems/opsandtactics/icons/weapons/guns/glock.webp",
  "system": {
    "description": "<h3>Weapon</h3><p>Upgrade Points:</p><p>F B</p><h3><span style=\"font-family: Roboto, sans-serif\">Single Action (SA)</span></h3><p style=\"box-sizing: border-box; user-select: text; scrollbar-width: thin; scrollbar-color: var(--color-scrollbar) var(--color-scrollbar-track); margin: 0.5em 0px; color: rgb(25, 24, 19); font-family: Roboto, sans-serif; font-size: 14px; font-style: normal; font-variant-ligatures: normal; font-variant-caps: normal; font-weight: 400; letter-spacing: normal; orphans: 2; text-indent: 0px; text-transform: none; widows: 2; word-spacing: 0px; -webkit-text-stroke-width: 0px; white-space: normal; text-decoration-thickness: initial; text-decoration-style: initial; text-decoration-color: initial; text-align: start\"><span style=\"font-family: Roboto, sans-serif\">Single Action requires the hammer to be pulled back before firing again. Single action firearms that take box magazines or have internal magazines are considered semi- automatic firearms. All Single Action firearms gain a +1 attack bonus on all single shot and potshot attacks. Single Action firearms with cylinders cost +1 Combat Points when performing a single shot attack.</span></p>",
    "type": "",
    "magazine": {
      "loaded": {},
      "type": "cartridge",
      "source": "",
      "insideOut": "external",
      "heatBase": 0
    },
    "range": "40ft",
    "crit": 16,
    "weaponMods": {},
    "actions": {
      "NVA771Fm": {
        "name": "Single Shot",
        "active": true,
        "check": {
          "flavor": "",
          "type": "ranged",
          "source": "",
          "inherent": "1",
          "ability": "mrk",
          "mods": {},
          "scaleAbility": 1,
          "ammo": true
        },
        "effect": {
          "flavor": "",
          "type": "",
          "source": "",
          "inherent": "",
          "ability": "",
          "mods": {},
          "scaleAbility": 1,
          "ammo": true
        },
        "ammo": 1,
        "cp": {
          "inherent": 6,
          "mods": {}
        },
        "display": true,
        "recoil": {
          "inherent": null,
          "mods": {},
          "active": false,
          "ammo": true
        },
        "dice": {
          "scaleCartridge": {
            "less": null,
            "bar": null,
            "more": null,
            "per": null,
            "scale": null
          }
        }
      },
      "DBIBJwPl": {
        "name": "Potshot",
        "active": true,
        "check": {
          "flavor": "",
          "type": "ranged",
          "source": "",
          "inherent": "-5",
          "ability": "mrk",
          "mods": {},
          "scaleAbility": 1,
          "ammo": true
        },
        "effect": {
          "flavor": "",
          "type": "",
          "source": "",
          "inherent": "",
          "ability": "",
          "mods": {},
          "scaleAbility": 1,
          "ammo": true
        },
        "ammo": 1,
        "cp": {
          "inherent": 4,
          "mods": {}
        },
        "display": true,
        "recoil": {
          "inherent": null,
          "mods": {},
          "active": false,
          "ammo": true
        },
        "dice": {
          "scaleCartridge": {
            "less": null,
            "bar": null,
            "more": null,
            "per": null,
            "scale": null
          }
        }
      },
      "lla0OcKp": {
        "name": "Double Tap",
        "active": true,
        "check": {
          "flavor": "",
          "type": "ranged",
          "source": "",
          "inherent": "",
          "ability": "mrk",
          "mods": {},
          "scaleAbility": 1,
          "ammo": true
        },
        "effect": {
          "flavor": "",
          "type": "",
          "source": "",
          "inherent": "",
          "ability": "",
          "mods": {},
          "scaleAbility": 1,
          "ammo": true
        },
        "ammo": 2,
        "cp": {
          "inherent": 6,
          "mods": {}
        },
        "display": true,
        "recoil": {
          "inherent": -3,
          "mods": {},
          "active": true,
          "ammo": true
        },
        "dice": {
          "scaleCartridge": {
            "less": 1,
            "bar": 3,
            "more": 2,
            "per": 3,
            "scale": 1
          }
        }
      }
    },
    "selectMod": "",
    "importFilter": "",
    "importMod": "",
    "gear": {
      "quantity": {
        "value": 1,
        "available": false
      },
      "size": "medium",
      "weight": 2.9,
      "cost": 25,
      "quality": "",
      "restriction": "L",
      "physical": true,
      "location": {
        "parent": "Loose",
        "note": ""
      },
      "resources": {},
      "tons": false,
      "capital": false
    },
    "minimized": false,
    "errorBase": 5,
    "damageBase": "",
    "flavorBase": ""
  },
  "effects": [],
  "flags": {
    "core": {}
  },
  "_stats": {
    "coreVersion": "11.315",
    "systemId": "opsandtactics",
    "systemVersion": "0.5.3",
    "createdTime": 1742545107334,
    "modifiedTime": 1742699965976,
    "lastModifiedBy": "awmzRJQcQXoX998M"
  },
  "folder": "n8behJCMxoC4mRT5",
  "ownership": {
    "default": 0,
    "qUf9EhhQBxZF46Rx": 3,
    "nc4XC244wznrOEZR": 3,
    "awmzRJQcQXoX998M": 3
  },
  "_id": "QKlo5GvA0EvWNRZ9",
  "sort": 600000,
  "_key": "!items!QKlo5GvA0EvWNRZ9"
}
